freshpaper.py
LICENSE
freshpaper_fixed-1.2.4.dist-info/entry_points.txt
freshpaper_fixed-1.2.4.dist-info/LICENSE
freshpaper_fixed-1.2.4.dist-info/METADATA
freshpaper_fixed-1.2.4.dist-info/WHEEL
freshpaper_fixed-1.2.4.dist-info/RECORD
